MANIFEST.in
setup.py
inoft_vocal_framework/__init__.py
inoft_vocal_framework/dummy_object.py
inoft_vocal_framework/exceptions.py
inoft_vocal_framework/general_utils.py
inoft_vocal_framework/messages.py
inoft_vocal_framework/nested_object_to_dict_with_auto_type_checking.py
inoft_vocal_framework/safe_dict.py
inoft_vocal_framework/session_utils.py
inoft_vocal_framework/bixby_core/__init__.py
inoft_vocal_framework/bixby_core/build.py
inoft_vocal_framework/bixby_core/generator.py
inoft_vocal_framework/bixby_core/templates/__init__.py
inoft_vocal_framework/bixby_core/templates/templates_access.py
inoft_vocal_framework/cli/__init__.py
inoft_vocal_framework/cli/aws_utils.py
inoft_vocal_framework/cli/cli_cache.py
inoft_vocal_framework/cli/cli_index.py
inoft_vocal_framework/cli/gui_handlers.py
inoft_vocal_framework/cli/new.py
inoft_vocal_framework/cli/botpress/__init__.py
inoft_vocal_framework/cli/botpress/cli_botpress.py
inoft_vocal_framework/cli/botpress/content_element_object.py
inoft_vocal_framework/cli/components/__init__.py
inoft_vocal_framework/cli/components/current_project_directory.py
inoft_vocal_framework/cli/deploy/__init__.py
inoft_vocal_framework/cli/deploy/cli_deploy.py
inoft_vocal_framework/cli/deploy/core.py
inoft_vocal_framework/cli/deploy/core_clients.py
inoft_vocal_framework/cli/deploy/policies.py
inoft_vocal_framework/databases/__init__.py
inoft_vocal_framework/databases/dynamodb/__init__.py
inoft_vocal_framework/databases/dynamodb/audio_editor_projects_dynamodb_client.py
inoft_vocal_framework/databases/dynamodb/dynamodb.py
inoft_vocal_framework/databases/dynamodb/dynamodb_core.py
inoft_vocal_framework/databases/dynamodb/dynamodb_utils.py
inoft_vocal_framework/databases/dynamodb/projects_text_contents_dynamodb_client.py
inoft_vocal_framework/databases/dynamodb/team_organization_projects_dynamodb_client.py
inoft_vocal_framework/img/__init__.py
inoft_vocal_framework/inoft_vocal_markup/__init__.py
inoft_vocal_framework/inoft_vocal_markup/deserializer.py
inoftvocal.egg-info/PKG-INFO
inoftvocal.egg-info/SOURCES.txt
inoftvocal.egg-info/dependency_links.txt
inoftvocal.egg-info/entry_points.txt
inoftvocal.egg-info/requires.txt
inoftvocal.egg-info/top_level.txt
