Metadata-Version: 1.0
Name: inoftvocal
Version: 0.90.5.7
Summary: Create advanced cross-platform skills for Alexa, Google Assistant and Samsung Bixby
Home-page: https://github.com/Robinson04/inoft_vocal_framework
Author: Inoft
Author-email: robinson@inoft.com
License: MIT
Platform: UNKNOWN
